<?xml version="1.0"?>
<annotation>
  <folder>Ayan</folder>
  <filename>cTDaR_t10413.jpg</filename>
  <path>D:\Egien Elites\TableNet\Dataset\Chunk\Ayan\cTDaR_t10413.jpg</path>
  <source>
    <database>Unknown</database>
  </source>
  <size>
    <width>794</width>
    <height>1059</height>
    <depth>3</depth>
  </size>
  <segmented>0</segmented>
  <object>
    <name>borderless</name>
    <pose>Unspecified</pose>
    <truncated>0</truncated>
    <difficult>0</difficult>
    <bndbox>
      <xmin>113</xmin>
      <ymin>352</ymin>
      <xmax>684</xmax>
      <ymax>836</ymax>
    </bndbox>
  </object>
</annotation>
